csulb_mock_dataset/__init__.py
csulb_mock_dataset/data.py
files/__init__.py
files/data.py
csulb_dataset-0.1.6.dist-info/METADATA
csulb_dataset-0.1.6.dist-info/WHEEL
csulb_dataset-0.1.6.dist-info/top_level.txt
csulb_dataset-0.1.6.dist-info/RECORD
