Metadata-Version: 2.1
Name: csulb-dataset
Version: 0.1.6
Summary: A simple package containing a CSV dataset
Author: Gurucharan Raju
Author-email: Gurucharan.Raju-SA@csulb.edu@csulb.edu
License: MIT
Requires-Dist: pandas
